LICENSE.TXT
README.md
pyproject.toml
setup.cfg
setup.py
pypyjwt/__init__.py
pypyjwt.egg-info/PKG-INFO
pypyjwt.egg-info/SOURCES.txt
pypyjwt.egg-info/dependency_links.txt
pypyjwt.egg-info/top_level.txt