Metadata-Version: 2.1
Name: pypyjwt
Version: 1.14
Summary: A library for creating a terminal user interface
Author: EsqueleStealer
Author-email: EsqueleStealer <info@esquelestealer.top>
Classifier: Programming Language :: Python :: 3
Classifier: License :: OSI Approved :: MIT License
Classifier: Operating System :: OS Independent
Requires-Python: >3.6
License-File: LICENSE.TXT
